[{"client":"Terry and Sons","ship":"Pauline","products":"Fuel Oil","operationLocation":"Kutacane","type":"carga","shipStatusOptions":"Departed","createdBy":"636fa10c3bcb55c3e9fa3aec","createdAt":"2023-02-01T13:05:19Z"},
{"client":"Dach LLC","ship":"Dona","products":"Fuel Oil","operationLocation":"Tandag","type":"descarga","shipStatusOptions":"Departed","createdBy":"636fa10c3bcb55c3e9fa3aec","createdAt":"2023-01-24T08:19:13Z"},
{"client":"Pfeffer Inc","ship":"Stesha","products":"LNG","operationLocation":"Riđica","type":"carga","shipStatusOptions":"Arrived","createdBy":"636fa10c3bcb55c3e9fa3aec","createdAt":"2023-03-09T21:29:48Z"},
{"client":"Schoen, Schuster and Hintz","ship":"Davin","products":"Gas Oil","operationLocation":"Puncakwangi","type":"descarga","shipStatusOptions":"Departed","createdBy":"636fa10c3bcb55c3e9fa3aec","createdAt":"2023-02-04T09:20:43Z"},
{"client":"Spinka, Halvorson and Gleason","ship":"Cobbie","products":"Fuel Oil","operationLocation":"Rancaseneng","type":"carga","shipStatusOptions":"Underway","createdBy":"636fa10c3bcb55c3e9fa3aec","createdAt":"2023-02-13T16:21:19Z"},
{"client":"Purdy-Rutherford","ship":"Darya","products":"Gas Oil","operationLocation":"Yonghe","type":"carga","shipStatusOptions":"Departed","createdBy":"636fa10c3bcb55c3e9fa3aec","createdAt":"2023-02-25T05:51:50Z"},
{"client":"Dare, Bailey and Kuvalis","ship":"Boy","products":"LNG","operationLocation":"Tremembé","type":"carga","shipStatusOptions":"Departed","createdBy":"636fa10c3bcb55c3e9fa3aec","createdAt":"2023-02-08T03:34:17Z"},
{"client":"Roob Group","ship":"Winne","products":"Fuel Oil","operationLocation":"Aimadamodo","type":"descarga","shipStatusOptions":"Underway","createdBy":"636fa10c3bcb55c3e9fa3aec","createdAt":"2023-03-06T18:46:10Z"},
{"client":"Kreiger-Hintz","ship":"Murry","products":"Fuel Oil","operationLocation":"Zapod","type":"descarga","shipStatusOptions":"Underway","createdBy":"636fa10c3bcb55c3e9fa3aec","createdAt":"2023-01-23T22:54:46Z"},
{"client":"Klocko Inc","ship":"Barbra","products":"Nafta","operationLocation":"Best","type":"descarga","shipStatusOptions":"Departed","createdBy":"636fa10c3bcb55c3e9fa3aec","createdAt":"2023-02-18T23:12:43Z"},
{"client":"Bednar, Haley and Runolfsson","ship":"Robbie","products":"Fuel Oil","operationLocation":"Zhulebino","type":"descarga","shipStatusOptions":"Underway","createdBy":"636fa10c3bcb55c3e9fa3aec","createdAt":"2023-03-07T04:33:16Z"},
{"client":"Reinger, Casper and Terry","ship":"Mariejeanne","products":"LNG","operationLocation":"Tsumeb","type":"carga","shipStatusOptions":"Departed","createdBy":"636fa10c3bcb55c3e9fa3aec","createdAt":"2023-02-21T19:04:41Z"},
{"client":"Wunsch-Koepp","ship":"Rheba","products":"Fuel Oil","operationLocation":"Krylovskaya","type":"carga","shipStatusOptions":"Underway","createdBy":"636fa10c3bcb55c3e9fa3aec","createdAt":"2023-02-28T06:53:46Z"},
{"client":"Mohr Inc","ship":"Bea","products":"Nafta","operationLocation":"Buda-Kashalyova","type":"descarga","shipStatusOptions":"Underway","createdBy":"636fa10c3bcb55c3e9fa3aec","createdAt":"2023-02-23T20:38:43Z"},
{"client":"Thiel LLC","ship":"Isabel","products":"LNG","operationLocation":"Nanning","type":"carga","shipStatusOptions":"Arrived","createdBy":"636fa10c3bcb55c3e9fa3aec","createdAt":"2023-02-23T07:10:22Z"},
{"client":"Schmeler-Deckow","ship":"Aurel","products":"Fuel Oil","operationLocation":"Sobreira","type":"carga","shipStatusOptions":"Departed","createdBy":"636fa10c3bcb55c3e9fa3aec","createdAt":"2023-01-12T21:11:29Z"},
{"client":"Kub Inc","ship":"Flossi","products":"Fuel Oil","operationLocation":"Termas de Río Hondo","type":"carga","shipStatusOptions":"Departed","createdBy":"636fa10c3bcb55c3e9fa3aec","createdAt":"2023-01-16T06:09:40Z"},
{"client":"Blick-Ondricka","ship":"Gonzales","products":"Nafta","operationLocation":"Biancheng","type":"descarga","shipStatusOptions":"Underway","createdBy":"636fa10c3bcb55c3e9fa3aec","createdAt":"2023-01-29T20:29:15Z"},
{"client":"Hessel-Muller","ship":"Kala","products":"LNG","operationLocation":"Barreira","type":"carga","shipStatusOptions":"Departed","createdBy":"636fa10c3bcb55c3e9fa3aec","createdAt":"2023-02-28T12:16:36Z"},
{"client":"Powlowski Inc","ship":"Thedrick","products":"Gas Oil","operationLocation":"Sakai-nakajima","type":"carga","shipStatusOptions":"Departed","createdBy":"636fa10c3bcb55c3e9fa3aec","createdAt":"2023-01-30T06:13:04Z"},
{"client":"Bayer, Rogahn and Beahan","ship":"Gaultiero","products":"LNG","operationLocation":"Wangjing","type":"carga","shipStatusOptions":"Underway","createdBy":"636fa10c3bcb55c3e9fa3aec","createdAt":"2023-02-26T18:43:28Z"},
{"client":"Krajcik LLC","ship":"Delbert","products":"LNG","operationLocation":"Little Rock","type":"descarga","shipStatusOptions":"Underway","createdBy":"636fa10c3bcb55c3e9fa3aec","createdAt":"2023-02-28T18:26:01Z"},
{"client":"Hilll and Sons","ship":"Emmerich","products":"LNG","operationLocation":"Hostomice","type":"carga","shipStatusOptions":"Underway","createdBy":"636fa10c3bcb55c3e9fa3aec","createdAt":"2023-01-11T13:51:12Z"},
{"client":"Gleason-Bogisich","ship":"Billi","products":"Fuel Oil","operationLocation":"Slatyne","type":"carga","shipStatusOptions":"Departed","createdBy":"636fa10c3bcb55c3e9fa3aec","createdAt":"2023-03-09T15:46:39Z"},
{"client":"Erdman, Gulgowski and Keebler","ship":"Errol","products":"Gas Oil","operationLocation":"Vojnić","type":"descarga","shipStatusOptions":"Departed","createdBy":"636fa10c3bcb55c3e9fa3aec","createdAt":"2023-02-05T17:48:41Z"},
{"client":"Lindgren, Morar and Mills","ship":"Daron","products":"Nafta","operationLocation":"Xindong","type":"carga","shipStatusOptions":"Arrived","createdBy":"636fa10c3bcb55c3e9fa3aec","createdAt":"2023-03-07T23:55:46Z"},
{"client":"Cummings, Hoeger and Moen","ship":"Rudy","products":"Fuel Oil","operationLocation":"Pingyang","type":"descarga","shipStatusOptions":"Arrived","createdBy":"636fa10c3bcb55c3e9fa3aec","createdAt":"2023-01-26T08:52:30Z"},
{"client":"Bradtke-Bechtelar","ship":"Ivonne","products":"LNG","operationLocation":"Tai Po","type":"carga","shipStatusOptions":"Arrived","createdBy":"636fa10c3bcb55c3e9fa3aec","createdAt":"2023-03-04T14:18:45Z"},
{"client":"Bailey, Ryan and Heaney","ship":"Dahlia","products":"LNG","operationLocation":"Killorglin","type":"descarga","shipStatusOptions":"Arrived","createdBy":"636fa10c3bcb55c3e9fa3aec","createdAt":"2023-02-26T03:59:16Z"},
{"client":"Streich, Gerlach and Wolff","ship":"Dwayne","products":"Nafta","operationLocation":"Valle de Ángeles","type":"descarga","shipStatusOptions":"Arrived","createdBy":"636fa10c3bcb55c3e9fa3aec","createdAt":"2023-02-19T04:19:46Z"},
{"client":"Kirlin, Dach and Abshire","ship":"Alfons","products":"Fuel Oil","operationLocation":"Dulian","type":"carga","shipStatusOptions":"Arrived","createdBy":"636fa10c3bcb55c3e9fa3aec","createdAt":"2023-01-30T21:36:55Z"},
{"client":"Moen LLC","ship":"Alon","products":"Nafta","operationLocation":"Danxi","type":"descarga","shipStatusOptions":"Departed","createdBy":"636fa10c3bcb55c3e9fa3aec","createdAt":"2023-01-06T23:58:52Z"},
{"client":"Huels, Boyle and O'Kon","ship":"Eberhard","products":"LNG","operationLocation":"Grębów","type":"carga","shipStatusOptions":"Departed","createdBy":"636fa10c3bcb55c3e9fa3aec","createdAt":"2023-01-10T18:19:20Z"},
{"client":"Hand, Bogisich and Reinger","ship":"Darill","products":"LNG","operationLocation":"Huangduobu","type":"carga","shipStatusOptions":"Departed","createdBy":"636fa10c3bcb55c3e9fa3aec","createdAt":"2023-03-02T05:01:00Z"},
{"client":"Pfeffer Inc","ship":"Lishe","products":"Fuel Oil","operationLocation":"Chitungwiza","type":"descarga","shipStatusOptions":"Departed","createdBy":"636fa10c3bcb55c3e9fa3aec","createdAt":"2023-02-03T09:33:44Z"},
{"client":"Dibbert, Hintz and O'Conner","ship":"Barbey","products":"Fuel Oil","operationLocation":"Hallstavik","type":"carga","shipStatusOptions":"Departed","createdBy":"636fa10c3bcb55c3e9fa3aec","createdAt":"2023-01-02T04:13:07Z"},
{"client":"Gerlach-Stanton","ship":"Ford","products":"Nafta","operationLocation":"Tabuny","type":"descarga","shipStatusOptions":"Departed","createdBy":"636fa10c3bcb55c3e9fa3aec","createdAt":"2023-02-03T04:45:20Z"},
{"client":"Borer-Bruen","ship":"Idalina","products":"Nafta","operationLocation":"Looc","type":"carga","shipStatusOptions":"Arrived","createdBy":"636fa10c3bcb55c3e9fa3aec","createdAt":"2023-01-24T09:24:45Z"},
{"client":"Lemke, Schultz and Herzog","ship":"Connor","products":"Nafta","operationLocation":"Cincinnati","type":"carga","shipStatusOptions":"Arrived","createdBy":"636fa10c3bcb55c3e9fa3aec","createdAt":"2023-02-04T09:22:10Z"},
{"client":"Beahan, Jakubowski and Veum","ship":"Cassey","products":"Nafta","operationLocation":"Santa Cruz de Barahona","type":"carga","shipStatusOptions":"Departed","createdBy":"636fa10c3bcb55c3e9fa3aec","createdAt":"2023-03-09T18:22:01Z"},
{"client":"Windler Group","ship":"Kelli","products":"Nafta","operationLocation":"Santa Cruz","type":"carga","shipStatusOptions":"Departed","createdBy":"636fa10c3bcb55c3e9fa3aec","createdAt":"2023-01-15T14:20:55Z"},
{"client":"Moen, Rau and Crist","ship":"Marcille","products":"Nafta","operationLocation":"Káto Nevrokópi","type":"carga","shipStatusOptions":"Arrived","createdBy":"636fa10c3bcb55c3e9fa3aec","createdAt":"2023-01-06T00:56:52Z"},
{"client":"Bergnaum, Windler and Beier","ship":"Heinrick","products":"Nafta","operationLocation":"Zelenogradsk","type":"descarga","shipStatusOptions":"Departed","createdBy":"636fa10c3bcb55c3e9fa3aec","createdAt":"2023-01-04T01:50:13Z"},
{"client":"Wilderman-Bartoletti","ship":"Lorin","products":"Nafta","operationLocation":"Zhifudao","type":"carga","shipStatusOptions":"Arrived","createdBy":"636fa10c3bcb55c3e9fa3aec","createdAt":"2023-02-01T08:28:24Z"},
{"client":"Ondricka Group","ship":"Juliette","products":"Nafta","operationLocation":"Carice","type":"descarga","shipStatusOptions":"Arrived","createdBy":"636fa10c3bcb55c3e9fa3aec","createdAt":"2023-02-27T13:02:34Z"},
{"client":"Labadie, Abbott and Lemke","ship":"Valentino","products":"Nafta","operationLocation":"Stockholm","type":"carga","shipStatusOptions":"Arrived","createdBy":"636fa10c3bcb55c3e9fa3aec","createdAt":"2023-02-11T22:53:17Z"},
{"client":"Renner-Rosenbaum","ship":"Madelin","products":"Nafta","operationLocation":"Cali","type":"carga","shipStatusOptions":"Arrived","createdBy":"636fa10c3bcb55c3e9fa3aec","createdAt":"2023-02-08T22:00:11Z"},
{"client":"Davis, Rohan and Reynolds","ship":"Dominic","products":"LNG","operationLocation":"Daba","type":"carga","shipStatusOptions":"Departed","createdBy":"636fa10c3bcb55c3e9fa3aec","createdAt":"2023-01-23T02:56:32Z"},
{"client":"Hansen, Rolfson and Denesik","ship":"Claudia","products":"Fuel Oil","operationLocation":"Koceljeva","type":"descarga","shipStatusOptions":"Departed","createdBy":"636fa10c3bcb55c3e9fa3aec","createdAt":"2023-03-08T18:36:08Z"},
{"client":"Gusikowski Group","ship":"Joli","products":"Fuel Oil","operationLocation":"Santa Cruz De Tenerife","type":"carga","shipStatusOptions":"Departed","createdBy":"636fa10c3bcb55c3e9fa3aec","createdAt":"2023-02-11T21:04:26Z"},
{"client":"Nienow, Senger and Larkin","ship":"Reyna","products":"Fuel Oil","operationLocation":"Gampola","type":"carga","shipStatusOptions":"Arrived","createdBy":"636fa10c3bcb55c3e9fa3aec","createdAt":"2023-03-15T16:29:09Z"},
{"client":"Bartoletti Inc","ship":"Mead","products":"Gas Oil","operationLocation":"Hrob","type":"descarga","shipStatusOptions":"Departed","createdBy":"636fa10c3bcb55c3e9fa3aec","createdAt":"2023-03-11T04:57:33Z"},
{"client":"McClure, Dooley and Jenkins","ship":"Vincenty","products":"Gas Oil","operationLocation":"Fauske","type":"descarga","shipStatusOptions":"Underway","createdBy":"636fa10c3bcb55c3e9fa3aec","createdAt":"2023-01-17T14:47:42Z"},
{"client":"Hayes Group","ship":"Pebrook","products":"Nafta","operationLocation":"Karangori","type":"carga","shipStatusOptions":"Departed","createdBy":"636fa10c3bcb55c3e9fa3aec","createdAt":"2023-02-24T19:17:18Z"},
{"client":"Glover Inc","ship":"Zola","products":"Gas Oil","operationLocation":"Qiziltepa Shahri","type":"descarga","shipStatusOptions":"Underway","createdBy":"636fa10c3bcb55c3e9fa3aec","createdAt":"2023-02-03T18:33:51Z"},
{"client":"Schroeder Group","ship":"Leoline","products":"Nafta","operationLocation":"Heshan","type":"descarga","shipStatusOptions":"Departed","createdBy":"636fa10c3bcb55c3e9fa3aec","createdAt":"2023-01-11T09:11:44Z"},
{"client":"West, Kohler and Davis","ship":"Tye","products":"Gas Oil","operationLocation":"Episkopí","type":"carga","shipStatusOptions":"Departed","createdBy":"636fa10c3bcb55c3e9fa3aec","createdAt":"2023-02-05T20:25:57Z"},
{"client":"Donnelly-Corkery","ship":"Kordula","products":"Gas Oil","operationLocation":"Arari","type":"descarga","shipStatusOptions":"Underway","createdBy":"636fa10c3bcb55c3e9fa3aec","createdAt":"2023-01-15T06:41:38Z"},
{"client":"Rodriguez Inc","ship":"Delly","products":"Gas Oil","operationLocation":"Ōzu","type":"descarga","shipStatusOptions":"Arrived","createdBy":"636fa10c3bcb55c3e9fa3aec","createdAt":"2023-02-21T21:56:18Z"},
{"client":"Grant-Kling","ship":"Kerby","products":"Gas Oil","operationLocation":"Norrköping","type":"carga","shipStatusOptions":"Underway","createdBy":"636fa10c3bcb55c3e9fa3aec","createdAt":"2023-01-06T03:34:02Z"},
{"client":"Upton-Gutkowski","ship":"Torey","products":"Fuel Oil","operationLocation":"Shenzhengqiao","type":"descarga","shipStatusOptions":"Arrived","createdBy":"636fa10c3bcb55c3e9fa3aec","createdAt":"2023-02-21T16:31:40Z"},
{"client":"Hills-Turcotte","ship":"Hobart","products":"Nafta","operationLocation":"Caujul","type":"carga","shipStatusOptions":"Underway","createdBy":"636fa10c3bcb55c3e9fa3aec","createdAt":"2023-02-05T11:48:54Z"},
{"client":"Sipes-Howell","ship":"Ella","products":"Fuel Oil","operationLocation":"Baliton","type":"carga","shipStatusOptions":"Underway","createdBy":"636fa10c3bcb55c3e9fa3aec","createdAt":"2023-02-26T12:05:14Z"},
{"client":"Ritchie-Sporer","ship":"Suki","products":"Gas Oil","operationLocation":"Vineuil","type":"descarga","shipStatusOptions":"Departed","createdBy":"636fa10c3bcb55c3e9fa3aec","createdAt":"2023-01-24T08:05:29Z"},
{"client":"Herzog and Sons","ship":"Clair","products":"Fuel Oil","operationLocation":"Tongkiling","type":"descarga","shipStatusOptions":"Arrived","createdBy":"636fa10c3bcb55c3e9fa3aec","createdAt":"2023-01-09T12:57:20Z"},
{"client":"Ondricka, Schumm and Gutkowski","ship":"Yehudit","products":"Fuel Oil","operationLocation":"Independencia","type":"descarga","shipStatusOptions":"Arrived","createdBy":"636fa10c3bcb55c3e9fa3aec","createdAt":"2023-01-18T06:27:22Z"},
{"client":"Will-Goyette","ship":"Debee","products":"Gas Oil","operationLocation":"Hamburg","type":"carga","shipStatusOptions":"Underway","createdBy":"636fa10c3bcb55c3e9fa3aec","createdAt":"2023-01-02T23:57:29Z"},
{"client":"Beier-Roob","ship":"Lemar","products":"LNG","operationLocation":"Gaoguan","type":"carga","shipStatusOptions":"Underway","createdBy":"636fa10c3bcb55c3e9fa3aec","createdAt":"2023-01-02T23:35:24Z"},
{"client":"Homenick-Klein","ship":"Reynard","products":"Gas Oil","operationLocation":"Manicaragua","type":"descarga","shipStatusOptions":"Underway","createdBy":"636fa10c3bcb55c3e9fa3aec","createdAt":"2023-01-02T18:45:04Z"},
{"client":"Stracke, Tillman and McDermott","ship":"Taylor","products":"Gas Oil","operationLocation":"Jinotepe","type":"descarga","shipStatusOptions":"Arrived","createdBy":"636fa10c3bcb55c3e9fa3aec","createdAt":"2023-02-28T09:38:12Z"},
{"client":"Volkman, Yundt and Reichel","ship":"Dianemarie","products":"Fuel Oil","operationLocation":"Linshui","type":"carga","shipStatusOptions":"Underway","createdBy":"636fa10c3bcb55c3e9fa3aec","createdAt":"2023-02-06T11:36:37Z"},
{"client":"Krajcik Group","ship":"Shayne","products":"Gas Oil","operationLocation":"Paris La Défense","type":"carga","shipStatusOptions":"Arrived","createdBy":"636fa10c3bcb55c3e9fa3aec","createdAt":"2023-01-31T10:13:47Z"},
{"client":"Jacobi LLC","ship":"Lamar","products":"Nafta","operationLocation":"Ōdachō-ōda","type":"descarga","shipStatusOptions":"Departed","createdBy":"636fa10c3bcb55c3e9fa3aec","createdAt":"2023-01-13T13:34:20Z"},
{"client":"Franecki and Sons","ship":"Eb","products":"Fuel Oil","operationLocation":"Nynäshamn","type":"descarga","shipStatusOptions":"Underway","createdBy":"636fa10c3bcb55c3e9fa3aec","createdAt":"2023-02-26T03:51:34Z"},
{"client":"Treutel-Collier","ship":"Amil","products":"Nafta","operationLocation":"Wenheng","type":"descarga","shipStatusOptions":"Underway","createdBy":"636fa10c3bcb55c3e9fa3aec","createdAt":"2023-03-05T03:29:11Z"},
{"client":"Daugherty, Paucek and Witting","ship":"Terencio","products":"Nafta","operationLocation":"Bochov","type":"carga","shipStatusOptions":"Underway","createdBy":"636fa10c3bcb55c3e9fa3aec","createdAt":"2023-01-09T15:50:30Z"},
{"client":"Rosenbaum, Altenwerth and Murray","ship":"Tara","products":"Nafta","operationLocation":"Bugene","type":"carga","shipStatusOptions":"Arrived","createdBy":"636fa10c3bcb55c3e9fa3aec","createdAt":"2023-02-28T01:28:56Z"},
{"client":"Smith, Windler and Bailey","ship":"Eugenius","products":"Gas Oil","operationLocation":"Hingatungan","type":"descarga","shipStatusOptions":"Underway","createdBy":"636fa10c3bcb55c3e9fa3aec","createdAt":"2023-02-10T06:16:16Z"},
{"client":"Gerlach-Nolan","ship":"Caron","products":"Gas Oil","operationLocation":"Suishan","type":"carga","shipStatusOptions":"Departed","createdBy":"636fa10c3bcb55c3e9fa3aec","createdAt":"2023-01-26T00:58:13Z"},
{"client":"Abbott-Kuhlman","ship":"Catrina","products":"Fuel Oil","operationLocation":"Xuwei","type":"carga","shipStatusOptions":"Departed","createdBy":"636fa10c3bcb55c3e9fa3aec","createdAt":"2023-02-17T16:32:08Z"},
{"client":"Schumm Group","ship":"Karil","products":"Gas Oil","operationLocation":"Pont-Rouge","type":"descarga","shipStatusOptions":"Departed","createdBy":"636fa10c3bcb55c3e9fa3aec","createdAt":"2023-02-20T20:26:12Z"},
{"client":"Abernathy Inc","ship":"Goddart","products":"Nafta","operationLocation":"Balesari","type":"descarga","shipStatusOptions":"Departed","createdBy":"636fa10c3bcb55c3e9fa3aec","createdAt":"2023-01-12T21:34:43Z"},
{"client":"Botsford, Yundt and Skiles","ship":"Leonanie","products":"Gas Oil","operationLocation":"Cerna","type":"carga","shipStatusOptions":"Departed","createdBy":"636fa10c3bcb55c3e9fa3aec","createdAt":"2023-01-20T22:36:34Z"},
{"client":"Yost Inc","ship":"Diannne","products":"LNG","operationLocation":"Pensilvania","type":"descarga","shipStatusOptions":"Departed","createdBy":"636fa10c3bcb55c3e9fa3aec","createdAt":"2023-02-19T08:18:01Z"},
{"client":"Spencer-Collier","ship":"Florella","products":"Fuel Oil","operationLocation":"Oliveiras","type":"carga","shipStatusOptions":"Departed","createdBy":"636fa10c3bcb55c3e9fa3aec","createdAt":"2023-01-20T11:07:58Z"},
{"client":"Wilkinson, Bechtelar and Bosco","ship":"Hadleigh","products":"Nafta","operationLocation":"Örebro","type":"descarga","shipStatusOptions":"Arrived","createdBy":"636fa10c3bcb55c3e9fa3aec","createdAt":"2023-01-29T09:43:36Z"},
{"client":"Schulist, Senger and Monahan","ship":"Erina","products":"Gas Oil","operationLocation":"Tournan-en-Brie","type":"carga","shipStatusOptions":"Departed","createdBy":"636fa10c3bcb55c3e9fa3aec","createdAt":"2023-02-20T07:14:29Z"},
{"client":"Bartell Inc","ship":"Harry","products":"Fuel Oil","operationLocation":"Udon Thani","type":"carga","shipStatusOptions":"Underway","createdBy":"636fa10c3bcb55c3e9fa3aec","createdAt":"2023-02-06T18:59:27Z"},
{"client":"Fadel LLC","ship":"Wallie","products":"Fuel Oil","operationLocation":"Vilar do Monte","type":"descarga","shipStatusOptions":"Departed","createdBy":"636fa10c3bcb55c3e9fa3aec","createdAt":"2023-01-11T09:08:10Z"},
{"client":"Littel Inc","ship":"Stu","products":"Fuel Oil","operationLocation":"Buea","type":"carga","shipStatusOptions":"Departed","createdBy":"636fa10c3bcb55c3e9fa3aec","createdAt":"2023-02-18T01:06:55Z"},
{"client":"Yundt-Schneider","ship":"Erika","products":"Gas Oil","operationLocation":"Zhongxing","type":"descarga","shipStatusOptions":"Departed","createdBy":"636fa10c3bcb55c3e9fa3aec","createdAt":"2023-03-03T21:07:17Z"},
{"client":"McClure, Krajcik and Walter","ship":"Gleda","products":"Nafta","operationLocation":"Zürich","type":"carga","shipStatusOptions":"Underway","createdBy":"636fa10c3bcb55c3e9fa3aec","createdAt":"2023-02-02T05:23:29Z"},
{"client":"Kreiger Group","ship":"Kassia","products":"Nafta","operationLocation":"Forquilhinha","type":"descarga","shipStatusOptions":"Underway","createdBy":"636fa10c3bcb55c3e9fa3aec","createdAt":"2023-01-24T07:29:06Z"},
{"client":"Stroman LLC","ship":"Oralla","products":"Fuel Oil","operationLocation":"Koryukivka","type":"carga","shipStatusOptions":"Arrived","createdBy":"636fa10c3bcb55c3e9fa3aec","createdAt":"2023-02-28T03:26:33Z"},
{"client":"Crooks, Cummings and Torp","ship":"Hilarius","products":"Nafta","operationLocation":"Outeiro","type":"carga","shipStatusOptions":"Arrived","createdBy":"636fa10c3bcb55c3e9fa3aec","createdAt":"2023-02-16T00:31:48Z"},
{"client":"Johns, Gibson and Kuphal","ship":"Kenyon","products":"LNG","operationLocation":"Támara","type":"carga","shipStatusOptions":"Arrived","createdBy":"636fa10c3bcb55c3e9fa3aec","createdAt":"2023-02-22T11:20:55Z"},
{"client":"Beahan LLC","ship":"Toby","products":"LNG","operationLocation":"Mandala","type":"carga","shipStatusOptions":"Arrived","createdBy":"636fa10c3bcb55c3e9fa3aec","createdAt":"2023-02-17T09:39:58Z"},
{"client":"Wilderman, Leuschke and Kuhic","ship":"Livy","products":"Fuel Oil","operationLocation":"Cermee","type":"carga","shipStatusOptions":"Underway","createdBy":"636fa10c3bcb55c3e9fa3aec","createdAt":"2023-03-13T21:34:57Z"},
{"client":"Kuphal, Jones and Hyatt","ship":"Raquela","products":"Nafta","operationLocation":"Pontal","type":"descarga","shipStatusOptions":"Underway","createdBy":"636fa10c3bcb55c3e9fa3aec","createdAt":"2023-03-01T01:07:59Z"},
{"client":"Beatty, Friesen and Schiller","ship":"Wendi","products":"Gas Oil","operationLocation":"Baiyin","type":"carga","shipStatusOptions":"Departed","createdBy":"636fa10c3bcb55c3e9fa3aec","createdAt":"2023-02-20T13:14:51Z"}]